gdrive_watcher/__init__.py
gdrive_watcher/__main__.py
gdrive_watcher/gdrive_authenticator.py
gdrive_watcher/gdrive_event.py
gdrive_watcher/gdrive_poll_watcher.py
gdrive_watcher/gdrive_reader.py
gdrive_watcher/gdrive_writer.py
gdrive_watcher/poll.py
gdrive_watcher-0.1.2.dist-info/METADATA
gdrive_watcher-0.1.2.dist-info/WHEEL
gdrive_watcher-0.1.2.dist-info/top_level.txt
gdrive_watcher-0.1.2.dist-info/RECORD
