Metadata-Version: 2.1
Name: gdrive-watcher
Version: 0.1.2
Summary: A utility to watch changes in a google drive folder.
Home-page: https://github.com/zzsi/gdrive-watcher
Author: Zhangzhang Si
Author-email: zhangzhang.si@gmail.com
License: MIT
Requires-Python: >=3.6
Requires-Dist: google-api-python-client (>=2.70.0)
Requires-Dist: python-dotenv (>=0.19.0)
